CHANGES
bootstrap.py
buildout.cfg
setup.cfg
setup.py
iw/__init__.py
iw.recipe.squid.egg-info/PKG-INFO
iw.recipe.squid.egg-info/SOURCES.txt
iw.recipe.squid.egg-info/dependency_links.txt
iw.recipe.squid.egg-info/entry_points.txt
iw.recipe.squid.egg-info/namespace_packages.txt
iw.recipe.squid.egg-info/not-zip-safe
iw.recipe.squid.egg-info/requires.txt
iw.recipe.squid.egg-info/top_level.txt
iw/recipe/__init__.py
iw/recipe/squid/README.txt
iw/recipe/squid/TODO
iw/recipe/squid/__init__.py
iw/recipe/squid/docs/README.txt
iw/recipe/squid/doctests/README.txt
iw/recipe/squid/templates/__init__.py
iw/recipe/squid/templates/iRedirector.py_tmpl
iw/recipe/squid/templates/squid.conf_tmpl
iw/recipe/squid/templates/squidAcl.py_tmpl
iw/recipe/squid/templates/squidRewriteRules.py_tmpl
iw/recipe/squid/templates/vhost_common_tmpl
iw/recipe/squid/templates/vhost_squid.conf_tmpl
iw/recipe/squid/templates/vhost_zcache_tmpl
iw/recipe/squid/templates/squid/__init__.py
iw/recipe/squid/templates/squid/squid_logrotate.conf_tmpl
iw/recipe/squid/templates/squid/squidctl_tmpl
iw/recipe/squid/tests/__init__.py
iw/recipe/squid/tests/test_squiddocs.py