Metadata-Version: 1.0
Name: iw.recipe.squid
Version: 1.0
Summary: ZC buildout recipe to configure an squid proxy for zope
Home-page: http://plone.org/products/iw-recipes
Author: Ingeniweb
Author-email: support@ingeniweb.com
License: GPL
Keywords: squid for zope
Platform: UNKNOWN
Classifier: Programming Language :: Python
Classifier: Topic :: Software Development :: Libraries :: Python Modules
Classifier: Topic :: Internet :: Proxy Servers
Classifier: Framework :: Zope2
